palworld_fix_uuid/__init__.py
palworld_fix_uuid/main.py
palworld_fix_uuid-0.1.4.dist-info/METADATA
palworld_fix_uuid-0.1.4.dist-info/WHEEL
palworld_fix_uuid-0.1.4.dist-info/entry_points.txt
palworld_fix_uuid-0.1.4.dist-info/RECORD
