Metadata-Version: 2.1
Name: palworld-fix-uuid
Version: 0.1.4
Summary: 
Author: Wonjoon Seol
Author-email: wonjoon.seol@gmail.com
Requires-Python: >=3.10,<4.0
Classifier: Programming Language :: Python :: 3
Classifier: Programming Language :: Python :: 3.10
Classifier: Programming Language :: Python :: 3.11
Classifier: Programming Language :: Python :: 3.12
Classifier: Programming Language :: Python :: 3.13
Requires-Dist: palworld-save-tools (>=0.23.0,<0.24.0)
Requires-Dist: rich (>=13.7.0,<14.0.0)
Requires-Dist: typer[rich] (>=0.12.3,<0.13.0)
